tagtor-0.2.4.dist-info/METADATA
tagtor-0.2.4.dist-info/WHEEL
tagtor/__init__.py
tagtor/tagtor.abi3.so
tagtor-0.2.4.dist-info/RECORD
