Metadata-Version: 2.4
Name: tagtor
Version: 0.2.4
Author: Sebastian Mohr <sebastian@mohrenclan.de>
Author-email: Sebastian Mohr <sebastian@mohrenclan.de>
